ReProv/__init__.py
ReProv/clients/__init__.py
ReProv/clients/base_client.py
ReProv/clients/provenance.py
ReProv/clients/workflow_execution.py
ReProv/clients/workflow_registry.py
ReProv/utils/__init__.py
ReProv/utils/authentication.py
ReProv-0.1.0.dist-info/LICENSE
ReProv-0.1.0.dist-info/METADATA
ReProv-0.1.0.dist-info/WHEEL
ReProv-0.1.0.dist-info/top_level.txt
ReProv-0.1.0.dist-info/RECORD
